mg_fastpurge/__init__.py
mg_fastpurge/purge.py
mg_fastpurge-0.1.5.dist-info/METADATA
mg_fastpurge-0.1.5.dist-info/WHEEL
mg_fastpurge-0.1.5.dist-info/entry_points.txt
mg_fastpurge-0.1.5.dist-info/RECORD
